GUI/__init__.py
GUI/mainwindow.py
GUI/rootmethod.py
GUI/welcome.py
ginrex/__init__.py
larch_app/__init__.py
larch_app/larch_app.py
tests/__init__.py
tests/test_job_1.py
ginrex-0.0.1.dist-info/METADATA
ginrex-0.0.1.dist-info/WHEEL
ginrex-0.0.1.dist-info/top_level.txt
ginrex-0.0.1.dist-info/RECORD
